uubed_native/__init__.py
uubed_native/ffi.py
uubed_native/libuubed_native.dylib
uubed_rs-0.1.0.dist-info/METADATA
uubed_rs-0.1.0.dist-info/WHEEL
uubed_rs-0.1.0.dist-info/RECORD
