Metadata-Version: 2.4
Name: uubed-rs
Version: 0.1.0
Classifier: Development Status :: 4 - Beta
Classifier: Intended Audience :: Developers
Classifier: Intended Audience :: Science/Research
Classifier: License :: OSI Approved :: MIT License
Classifier: Operating System :: OS Independent
Classifier: Programming Language :: Rust
Classifier: Programming Language :: Python :: 3
Classifier: Programming Language :: Python :: 3.8
Classifier: Programming Language :: Python :: 3.9
Classifier: Programming Language :: Python :: 3.10
Classifier: Programming Language :: Python :: 3.11
Classifier: Programming Language :: Python :: 3.12
Classifier: Topic :: Scientific/Engineering
Classifier: Topic :: Software Development :: Libraries
Classifier: Topic :: System :: Archiving :: Compression
Requires-Dist: numpy>=1.20.0
Requires-Dist: pytest>=7.0 ; extra == 'dev'
Requires-Dist: pytest-benchmark>=4.0 ; extra == 'dev'
Requires-Dist: numpy>=1.20.0 ; extra == 'dev'
Requires-Dist: maturin>=1.0,<2.0 ; extra == 'dev'
Provides-Extra: dev
Summary: High-performance Rust core for position-safe embedding encoding (QuadB64 family)
Keywords: encoding,embeddings,base64,rust,performance
Author: Adam Twardoch <adam+github@twardoch.com>
Author-email: Adam Twardoch <adam+github@twardoch.com>
Maintainer-email: Adam Twardoch <adam+github@twardoch.com>
License: MIT
Requires-Python: >=3.8
Project-URL: Homepage, https://github.com/twardoch/uubed-rs
Project-URL: Repository, https://github.com/twardoch/uubed-rs
Project-URL: Documentation, https://uubed.readthedocs.io/
Project-URL: Issues, https://github.com/twardoch/uubed-rs/issues
Project-URL: Changelog, https://github.com/twardoch/uubed-rs/blob/main/CHANGELOG.md
